{
	"info": {
		"_postman_id": "357d5c18-043d-4cbb-809e-b7c53d5a199c",
		"name": "Crud personas",
		"schema": "https://schema.getpostman.com/json/collection/v2.1.0/collection.json",
		"_exporter_id": "20927308",
		"_collection_link": "https://planetary-water-396974.postman.co/workspace/Team-Workspace~dfd0c296-7426-49dc-8b42-2506e032582f/collection/20927308-357d5c18-043d-4cbb-809e-b7c53d5a199c?action=share&source=collection_link&creator=20927308"
	},
	"item": [
		{
			"name": "obtenerTodos",
			"request": {
				"method": "GET",
				"header": [],
				"url": {
					"raw": "http://localhost:8080/api/personas",
					"protocol": "http",
					"host": [
						"localhost"
					],
					"port": "8080",
					"path": [
						"api",
						"personas"
					]
				}
			},
			"response": []
		},
		{
			"name": "obtenerPorId",
			"request": {
				"method": "GET",
				"header": [],
				"url": {
					"raw": "http://localhost:8080/api/personas/1",
					"protocol": "http",
					"host": [
						"localhost"
					],
					"port": "8080",
					"path": [
						"api",
						"personas",
						"1"
					]
				}
			},
			"response": []
		},
		{
			"name": "crear",
			"request": {
				"method": "POST",
				"header": [],
				"body": {
					"mode": "raw",
					"raw": "{\r\n    \"nombres\": \"Juan Ignacio Perez\",\r\n    \"email\": \"ji.perez@gmail.com\"\r\n}",
					"options": {
						"raw": {
							"language": "json"
						}
					}
				},
				"url": {
					"raw": "http://localhost:8080/api/personas",
					"protocol": "http",
					"host": [
						"localhost"
					],
					"port": "8080",
					"path": [
						"api",
						"personas"
					]
				}
			},
			"response": []
		},
		{
			"name": "actualizar",
			"request": {
				"method": "PUT",
				"header": [],
				"body": {
					"mode": "raw",
					"raw": "{\r\n    \"nombres\": \"Lionel Messi\",\r\n    \"email\": \"l.messi@gmail.com\"\r\n}",
					"options": {
						"raw": {
							"language": "json"
						}
					}
				},
				"url": {
					"raw": "http://localhost:8080/api/personas/1",
					"protocol": "http",
					"host": [
						"localhost"
					],
					"port": "8080",
					"path": [
						"api",
						"personas",
						"1"
					]
				}
			},
			"response": []
		},
		{
			"name": "eliminar",
			"request": {
				"method": "DELETE",
				"header": [],
				"body": {
					"mode": "raw",
					"raw": "",
					"options": {
						"raw": {
							"language": "json"
						}
					}
				},
				"url": {
					"raw": "http://localhost:8080/api/personas/1",
					"protocol": "http",
					"host": [
						"localhost"
					],
					"port": "8080",
					"path": [
						"api",
						"personas",
						"1"
					]
				}
			},
			"response": []
		}
	]
}